nicotools/__init__.py
nicotools/download.py
nicotools/mylist.py
nicotools/utils.py
nicotools-1.0.4.dist-info/METADATA
nicotools-1.0.4.dist-info/RECORD
nicotools-1.0.4.dist-info/WHEEL
nicotools-1.0.4.dist-info/entry_points.txt
nicotools-1.0.4.dist-info/top_level.txt
