Metadata-Version: 2.1
Name: nicotools
Version: 1.0.4
Summary: Downloading videos, comments and thumbnails and handling your Mylists on niconico (ニコニコ動画).
Home-page: https://github.com/mo-san/niconico-tools
Author: Masaki Taniguchi
Author-email: window100@gmail.com
License: MIT License
Keywords: niconico,nicovideo,ニコニコ動画
Platform: UNKNOWN
Classifier: Development Status :: 5 - Production/Stable
Classifier: Intended Audience :: End Users/Desktop
Classifier: License :: OSI Approved :: MIT License
Classifier: Natural Language :: Japanese
Classifier: Programming Language :: Python :: 3 :: Only
Classifier: Programming Language :: Python :: 3.6
Classifier: Programming Language :: Python :: 3.7
Requires-Dist: requests
Requires-Dist: prettytable
Requires-Dist: bs4
Requires-Dist: aiohttp
Requires-Dist: tqdm
Requires-Dist: multidict
